absabranchsortcodes/__init__.py
absabranchsortcodes/absabranchsortcodes.py
absabranchsortcodes-0.0.1.dist-info/LICENSE
absabranchsortcodes-0.0.1.dist-info/METADATA
absabranchsortcodes-0.0.1.dist-info/WHEEL
absabranchsortcodes-0.0.1.dist-info/top_level.txt
absabranchsortcodes-0.0.1.dist-info/RECORD
