Metadata-Version: 2.1
Name: absabranchsortcodes
Version: 0.0.1
Summary: ABSA Branch Sort Codes Generator.
Home-page: UNKNOWN
Author: Hendrik du Toit
Author-email: hendrik@brightedge.co.za
License: UNKNOWN
Platform: UNKNOWN
Classifier: Programming Language :: Python :: 3
Classifier: License :: Other/Proprietary License
Classifier: Operating System :: OS Independent
Requires-Python: >=3.6
Requires-Dist: termcolor
Requires-Dist: black
Requires-Dist: ipython
Requires-Dist: twine
